embutils/__init__.py
embutils/repo/__init__.py
embutils/repo/build.py
embutils/repo/templates/template_version_c.h
embutils/serial/__init__.py
embutils/serial/device.py
embutils/serial/interface.py
embutils/serial/stream.py
embutils/utils/__init__.py
embutils/utils/binary.py
embutils/utils/bytes.py
embutils/utils/cobs.py
embutils/utils/common.py
embutils/utils/crc.py
embutils/utils/enum.py
embutils/utils/env.py
embutils/utils/events.py
embutils/utils/logger.py
embutils/utils/math.py
embutils/utils/parsed.py
embutils/utils/path.py
embutils/utils/serialized.py
embutils/utils/service.py
embutils/utils/stream.py
embutils/utils/subprocess.py
embutils/utils/threading.py
embutils/utils/time.py
embutils-0.8.6.dist-info/entry_points.txt
embutils-0.8.6.dist-info/WHEEL
embutils-0.8.6.dist-info/METADATA
embutils-0.8.6.dist-info/RECORD
