Metadata-Version: 2.1
Name: embutils
Version: 0.8.6
Summary: Python utilities for embedded projects
Home-page: https://github.com/cwichel/embutils
License: MIT
Keywords: python,embedded,utilities
Author: Christian Wiche
Author-email: cwichel@gmail.com
Requires-Python: >=3.7,<4.0
Classifier: License :: OSI Approved :: MIT License
Classifier: Programming Language :: Python :: 3
Classifier: Programming Language :: Python :: 3.10
Classifier: Programming Language :: Python :: 3.7
Classifier: Programming Language :: Python :: 3.8
Classifier: Programming Language :: Python :: 3.9
Classifier: Topic :: Utilities
Requires-Dist: PyYAML (>=6.0,<7.0)
Requires-Dist: attrs (>=21.2.0,<22.0.0)
Requires-Dist: cattrs (>=1.10.0,<2.0.0)
Requires-Dist: intelhex (>=2.3.0,<3.0.0)
Requires-Dist: pyserial (>=3.5,<4.0)
